pesi/__init__.py
pesi/main.py
pesi/lib/__init__.py
pesi/lib/docker/__init__.py
pesi/lib/docker/auth.py
pesi/lib/docker/client.py
pesi/lib/docker/constants.py
pesi/lib/docker/errors.py
pesi/lib/docker/tls.py
pesi/lib/docker/version.py
pesi/lib/docker/api/__init__.py
pesi/lib/docker/api/build.py
pesi/lib/docker/api/client.py
pesi/lib/docker/api/config.py
pesi/lib/docker/api/container.py
pesi/lib/docker/api/daemon.py
pesi/lib/docker/api/exec_api.py
pesi/lib/docker/api/image.py
pesi/lib/docker/api/network.py
pesi/lib/docker/api/plugin.py
pesi/lib/docker/api/secret.py
pesi/lib/docker/api/service.py
pesi/lib/docker/api/swarm.py
pesi/lib/docker/api/volume.py
pesi/lib/docker/credentials/__init__.py
pesi/lib/docker/credentials/constants.py
pesi/lib/docker/credentials/errors.py
pesi/lib/docker/credentials/store.py
pesi/lib/docker/credentials/utils.py
pesi/lib/docker/models/__init__.py
pesi/lib/docker/models/configs.py
pesi/lib/docker/models/containers.py
pesi/lib/docker/models/images.py
pesi/lib/docker/models/networks.py
pesi/lib/docker/models/nodes.py
pesi/lib/docker/models/plugins.py
pesi/lib/docker/models/resource.py
pesi/lib/docker/models/secrets.py
pesi/lib/docker/models/services.py
pesi/lib/docker/models/swarm.py
pesi/lib/docker/models/volumes.py
pesi/lib/docker/transport/__init__.py
pesi/lib/docker/transport/basehttpadapter.py
pesi/lib/docker/transport/npipeconn.py
pesi/lib/docker/transport/npipesocket.py
pesi/lib/docker/transport/sshconn.py
pesi/lib/docker/transport/ssladapter.py
pesi/lib/docker/transport/unixconn.py
pesi/lib/docker/types/__init__.py
pesi/lib/docker/types/base.py
pesi/lib/docker/types/containers.py
pesi/lib/docker/types/daemon.py
pesi/lib/docker/types/healthcheck.py
pesi/lib/docker/types/networks.py
pesi/lib/docker/types/services.py
pesi/lib/docker/types/swarm.py
pesi/lib/docker/utils/__init__.py
pesi/lib/docker/utils/build.py
pesi/lib/docker/utils/config.py
pesi/lib/docker/utils/decorators.py
pesi/lib/docker/utils/fnmatch.py
pesi-0.0.4.dist-info/METADATA
pesi-0.0.4.dist-info/WHEEL
pesi-0.0.4.dist-info/entry_points.txt
pesi-0.0.4.dist-info/top_level.txt
pesi-0.0.4.dist-info/RECORD
