Metadata-Version: 2.1
Name: pesi
Version: 0.0.4
Summary: Build your Python project to Docker image on remote Docker server
Home-page: https://github.com/pesi1874/pesi
Author: pesi1874
Author-email: pesi1874@gmail.com
License: UNKNOWN
Platform: UNKNOWN
Classifier: Development Status :: 4 - Beta
Classifier: Intended Audience :: Developers
Classifier: Programming Language :: Python :: 3
Classifier: License :: OSI Approved :: Apache Software License
Classifier: Operating System :: POSIX :: Linux
Requires-Python: >=3.5
Requires-Dist: click (>=7.1.1)
